MANIFEST.in
README
setup.py
examples/java/consumer/Consumer.java
examples/java/ztreamyPublisher/src/main/java/ztreamy/Event.java
examples/java/ztreamyPublisher/src/main/java/ztreamy/JSONSerializer.java
examples/java/ztreamyPublisher/src/main/java/ztreamy/Publisher.java
examples/java/ztreamyPublisher/src/main/java/ztreamy/PublisherHC.java
examples/java/ztreamyPublisher/src/main/java/ztreamy/Serializer.java
examples/java/ztreamyPublisher/src/main/java/ztreamy/ZtreamySerializer.java
examples/java/ztreamyPublisher/src/test/java/Test.java
examples/java/ztreamyPublisher/src/test/java/TestEvent.java
examples/java/ztreamyPublisher/src/test/java/TestHC.java
examples/python/consumer_async.py
examples/python/consumer_filter.py
examples/python/consumer_sync.py
examples/python/publisher_async.py
examples/python/publisher_sync.py
examples/python/server.py
ztreamy/__init__.py
ztreamy/client.py
ztreamy/dispatchers.py
ztreamy/events.py
ztreamy/events_buffer.py
ztreamy/filters.py
ztreamy/loganalyzer.py
ztreamy/logger.py
ztreamy/rdfevents.py
ztreamy/relay.py
ztreamy/server.py
ztreamy/stats.py
ztreamy/synchronous_client.py
ztreamy.egg-info/PKG-INFO
ztreamy.egg-info/SOURCES.txt
ztreamy.egg-info/dependency_links.txt
ztreamy.egg-info/requires.txt
ztreamy.egg-info/top_level.txt
ztreamy/casestudy/__init__.py
ztreamy/casestudy/processor.py
ztreamy/casestudy/source.py
ztreamy/data/static
ztreamy/data/static/dashboard.html
ztreamy/data/static/ztreamy.css
ztreamy/data/static/ztreamy.js
ztreamy/examples/__init__.py
ztreamy/examples/cosmAQESensor.py
ztreamy/examples/counterApp.py
ztreamy/examples/geonamesApp.py
ztreamy/examples/twitterFollowerBot.py
ztreamy/examples/twitterSensor.py
ztreamy/examples/wikipediaSensor.py
ztreamy/experiments/__init__.py
ztreamy/experiments/analyze_compression.py
ztreamy/experiments/analyze_manyc_log.py
ztreamy/experiments/dataset_stats.py
ztreamy/experiments/download_identica.py
ztreamy/experiments/extract_body.py
ztreamy/tools/__init__.py
ztreamy/tools/bayeux.py
ztreamy/tools/cputime.py
ztreamy/tools/event_source.py
ztreamy/tools/many_clients.py
ztreamy/tools/replay.py
ztreamy/tools/utils.py
