Metadata-Version: 1.0
Name: ztreamy
Version: 0.5
Summary: A framework for publishing semantic events on the Web
Home-page: http://www.ztreamy.org/
Author: Jesus Arias Fisteus
Author-email: jfisteus@gmail.com
License: GPL3
Keywords: rdf sensors web semantic-sensor-web
Platform: UNKNOWN
